poormanray/__init__.py
poormanray/cli.py
poormanray/utils.py
poormanray/version.py
poormanray-0.1.0.dist-info/METADATA
poormanray-0.1.0.dist-info/WHEEL
poormanray-0.1.0.dist-info/entry_points.txt
poormanray-0.1.0.dist-info/licenses/LICENSE
poormanray-0.1.0.dist-info/RECORD
