Metadata-Version: 2.4
Name: poormanray
Version: 0.1.0
Summary: A minimal alternative to Ray for distributed data processing on EC2 instances
Project-URL: Homepage, https://github.com/allenai/poormanray
Project-URL: Repository, https://github.com/allenai/poormanray
Project-URL: Issues, https://github.com/allenai/poormanray/issues
Author-email: Luca Soldaini <luca@soldaini.net>
License-Expression: Apache-2.0
License-File: LICENSE
Keywords: aws,cluster,data-processing,distributed,ec2,ray
Classifier: Development Status :: 4 - Beta
Classifier: Environment :: Console
Classifier: Intended Audience :: Developers
Classifier: Intended Audience :: Science/Research
Classifier: License :: OSI Approved :: Apache Software License
Classifier: Operating System :: OS Independent
Classifier: Programming Language :: Python :: 3
Classifier: Programming Language :: Python :: 3.10
Classifier: Programming Language :: Python :: 3.11
Classifier: Programming Language :: Python :: 3.12
Classifier: Topic :: System :: Distributed Computing
Requires-Python: >=3.10
Requires-Dist: boto3>=1.26.0
Requires-Dist: click>=8.0.0
Requires-Dist: paramiko>=3.0.0
Provides-Extra: dev
Requires-Dist: boto3-stubs[ec2,ssm]; extra == 'dev'
Requires-Dist: mypy; extra == 'dev'
Requires-Dist: ruff; extra == 'dev'
